sixs_bin/__init__.py
sixs_bin/__main__.py
sixs_bin/_cli.py
sixs_bin/py.typed
sixs_bin/sixsV1.1
sixs_bin/sixsV2.1
6s_bin-0.11.3.dist-info/LICENSE
6s_bin-0.11.3.dist-info/METADATA
6s_bin-0.11.3.dist-info/WHEEL
6s_bin-0.11.3.dist-info/RECORD
