Metadata-Version: 2.1
Name: 6s-bin
Version: 0.11.3
Summary: Compiled binaries for the 6S Radiative Transfer Model exposed as package resources.
Home-page: https://github.com/brianschubert/6s-bin
License: Apache-2.0
Author: Brian Schubert
Author-email: schubert.b@northeastern.edu
Requires-Python: >=3.9,<4.0
Classifier: Development Status :: 3 - Alpha
Classifier: Intended Audience :: Science/Research
Classifier: License :: OSI Approved :: Apache Software License
Classifier: Programming Language :: Fortran
Classifier: Programming Language :: Python :: 3
Classifier: Programming Language :: Python :: 3.9
Classifier: Programming Language :: Python :: 3.10
Classifier: Programming Language :: Python :: 3.11
Classifier: Programming Language :: Python :: 3.12
Classifier: Topic :: Scientific/Engineering :: Atmospheric Science
Classifier: Typing :: Typed
Provides-Extra: wrapper
Requires-Dist: py6s (>=1.9.2,<2.0.0) ; extra == "wrapper"
Requires-Dist: python-dateutil (>=2.8.2,<3.0.0) ; extra == "wrapper"
Requires-Dist: typing-extensions (>=3.10)
Project-URL: Repository, https://github.com/brianschubert/6s-bin
